{
    "Plant": "Bathtub",
    "Controller": "Classic",
    "initial_kp": 0.5,
    "initial_kd": 0.5,
    "initial_ki": 0.5,
    "initial_q1": 0.4,
    "initial_q2": 0.5,
    "Random_seed": 42,
    "Epochs": 100,
    "Simulation_steps_per_epoch": 10,
    "Learning_rate": 0.01,
    "Disturbance_range": [-0.01,0.01],
    "Neural_network_layers": [3],
    "Neural_network_activation_function": "tanh",
    "Neural_network_param_range_weights": [0.05,0.2],
    "Neural_network_param_range_bias": [0,0.02],
    "Bathtub_area": 150,
    "Bathtub_cross_sectional_area": 10,
    "Bathtub_height":200,
    "Bathtub_gravity": 9.81,
    "Cournot_max_price": 3,
    "Cournot_marginal_cost": 0.1,
    "Cournot_target": 0.5,
    "Furnace_heat_capacity": 1000,
    "Furnace_heat_loss_coefficient": 10,
    "Ambient_temperature": 25,
    "Furnace_initial_temperature": 150,
    "Furnace_target_temperature": 200, 
    "Visualization_flag": true
}
